MANIFEST.in
README.md
setup.py
ltsa/__init__.py
ltsa/_local_tangent_space_alignment.py
ltsa.egg-info/PKG-INFO
ltsa.egg-info/SOURCES.txt
ltsa.egg-info/dependency_links.txt
ltsa.egg-info/not-zip-safe
ltsa.egg-info/top_level.txt
ltsa/testing/__init__.py
ltsa/testing/test_debugscript.py
ltsa/testing/test_ltsamodule.py
ltsa/testing/test_preimage.py
ltsa/testing/test_utils.py
ltsa/utils/__init__.py
ltsa/utils/preprocessing.py