Metadata-Version: 1.1
Name: ltsa
Version: 0.2
Summary: Package for Local Tangent Space Alignment manfiold learning.
Home-page: https://gitlab.com/charles1992/ltsa
Author: Charles gadd
Author-email: cwlgadd@gmail.com
License: Creative Commons Attribution-Noncommercial-Share Alike license
Download-URL: https://gitlab.com/charles1992/ltsa
Platform: UNKNOWN
